{
  "nightly": {
    "description": "Unstable",
    "hide": false,
    "last_updated": "2025-01-07T07:05:38.000Z",
    "last_updated_url": "https://github.com/hotio/jellyfin/actions/runs/12646739244",
    "latest": false,
    "tags": [
      "nightly",
      "nightly-2025010605",
      "nightly-e372221"
    ]
  },
  "release": {
    "description": "Stable",
    "hide": false,
    "last_updated": "2025-01-07T07:04:57.000Z",
    "last_updated_url": "https://github.com/hotio/jellyfin/actions/runs/12646729443",
    "latest": true,
    "tags": [
      "release",
      "release-10.10.3",
      "release-8c7b5e3"
    ]
  }
}
